{"map_id": 6775, "uuid": "f29349ee-ee4e-5602-ab20-94e8a85b1334", "layout_version": 1, "natural_key": "svtk_place_le_sea_06775", "source_place_hash": "8c24e1f808951e702ca67443687a48d705073bef541483b98aaa854dcc0c394c", "source_build_rule_hash": "9a6a7f63d350dfd63656334a21d21ffe3ee2613681e42e4d9412b92e8946d06f", "topology_version": 1, "biome": "sea", "era": "le", "zone": "trung_bo", "tier": 4, "safe_zone": false, "grid_w": 56, "grid_h": 42, "background": {"art_group": "sea_le_t4"}, "walk_mask": {"encoding": "rle", "width": 56, "height": 42, "data": [[0, 1], [2, 1], [0, 1], [2, 1], [0, 1], [2, 1], [0, 1], [2, 1], [0, 1], [2, 1], [0, 1], [2, 1], [3, 1], [2, 1], [0, 1], [2, 1], [0, 1], [2, 1], [0, 1], [1, 1], [0, 1], [2, 1], [0, 1], [2, 1], [3, 1], [2, 1], [0, 1], [2, 1], [0, 1], [2, 1], [0, 1], [2, 1], [0, 1], [2, 1], [0, 1], [2, 1], [0, 1], [3, 1], [0, 1], [2, 1], [0, 1], [2, 1], [0, 1], [2, 1], [0, 1], [1, 1], [0, 1], [2, 1], [0, 1], [2, 1], [0, 1], [2, 1], [0, 1], [2, 1], [0, 1], [2, 22], [3, 1], [2, 31], [1, 1], [2, 2], [0, 29], [2, 1], [0, 1], [2, 1], [0, 1], [2, 1], [3, 1], [2, 1], [0, 1], [2, 1], [0, 1], [2, 1], [0, 1], [2, 1], [0, 1], [2, 1], [0, 1], [2, 1], [0, 1], [1, 1], [0, 1], [2, 1], [0, 1], [2, 1], [0, 1], [2, 1], [3, 1], [2, 4], [1, 1], [2, 24], [0, 1], [3, 1], [2, 26], [0, 1], [2, 1], [0, 1], [3, 1], [0, 1], [2, 1], [0, 1], [2, 1], [0, 1], [2, 1], [0, 1], [2, 1], [0, 1], [2, 1], [0, 1], [2, 1], [0, 1], [2, 1], [0, 1], [2, 1], [0, 1], [2, 1], [0, 1], [2, 1], [0, 1], [2, 1], [0, 1], [2, 1], [0, 1], [2, 1], [0, 1], [2, 1], [0, 1], [2, 1], [0, 1], [2, 1], [0, 1], [2, 1], [0, 1], [2, 1], [0, 1], [2, 1], [0, 1], [2, 1], [0, 1], [2, 1], [0, 1], [2, 1], [0, 1], [2, 1], [0, 1], [3, 1], [0, 1], [2, 1], [0, 1], [2, 9], [3, 1], [2, 18], [3, 1], [0, 1], [2, 13], [1, 1], [2, 8], [3, 1], [2, 4], [0, 1], [2, 1], [0, 1], [1, 1], [0, 1], [2, 1], [0, 1], [2, 1], [0, 1], [2, 1], [0, 1], [2, 1], [0, 1], [2, 1], [0, 1], [2, 1], [0, 1], [2, 1], [0, 1], [2, 1], [0, 1], [2, 1], [0, 1], [2, 1], [0, 1], [2, 1], [0, 1], [2, 1], [0, 27], [2, 1], [1, 1], [2, 3], [3, 1], [2, 7], [3, 1], [2, 4], [3, 1], [2, 10], [0, 1], [2, 3], [3, 1], [2, 17], [3, 1], [2, 5], [0, 1], [2, 1], [0, 1], [2, 1], [0, 1], [3, 1], [0, 1], [2, 1], [0, 1], [2, 1], [0, 1], [2, 1], [0, 1], [2, 1], [0, 1], [2, 1], [0, 1], [2, 1], [0, 1], [2, 1], [0, 1], [2, 1], [0, 1], [2, 1], [0, 1], [2, 1], [0, 1], [2, 1], [0, 1], [2, 1], [0, 1], [2, 1], [0, 1], [2, 1], [0, 1], [2, 1], [3, 1], [2, 1], [0, 1], [2, 1], [0, 1], [2, 1], [0, 1], [2, 1], [0, 1], [2, 1], [0, 1], [2, 1], [0, 1], [2, 1], [0, 1], [2, 1], [0, 1], [2, 1], [0, 1], [2, 14], [3, 1], [2, 14], [0, 1], [2, 27], [0, 1], [2, 1], [0, 1], [1, 1], [0, 1], [2, 1], [0, 1], [2, 1], [0, 1], [2, 1], [0, 1], [2, 1], [0, 1], [2, 1], [0, 1], [2, 1], [0, 1], [2, 1], [0, 1], [2, 1], [0, 1], [2, 1], [0, 1], [2, 1], [0, 1], [2, 1], [0, 1], [2, 1], [0, 27], [2, 2], [1, 1], [2, 10], [3, 1], [2, 6], [3, 1], [2, 1], [1, 1], [2, 6], [0, 1], [2, 3], [3, 1], [2, 21], [3, 1], [2, 1], [0, 1], [2, 1], [3, 1], [2, 1], [0, 1], [2, 1], [0, 1], [2, 1], [0, 1], [2, 1], [3, 1], [2, 1], [0, 1], [2, 1], [0, 1], [2, 1], [0, 1], [2, 1], [0, 1], [2, 1], [0, 1], [2, 1], [3, 1], [2, 1], [0, 1], [2, 1], [0, 1], [2, 1], [0, 1], [2, 1], [0, 1], [2, 1], [0, 1], [2, 1], [0, 1], [2, 1], [0, 1], [2, 1], [0, 1], [2, 1], [0, 1], [2, 1], [0, 1], [2, 1], [0, 1], [2, 1], [0, 1], [2, 1], [3, 1], [2, 1], [0, 1], [2, 1], [0, 1], [2, 1], [0, 1], [2, 3], [0, 27], [2, 1], [1, 1], [2, 12], [3, 1], [2, 12], [0, 1], [2, 1], [0, 1], [2, 1], [0, 1], [2, 1], [0, 1], [2, 1], [0, 1], [2, 1], [0, 1], [2, 1], [0, 1], [2, 1], [0, 1], [2, 1], [0, 1], [2, 1], [0, 1], [2, 1], [0, 1], [2, 1], [0, 1], [1, 1], [0, 1], [2, 1], [3, 1], [2, 1], [0, 1], [2, 1], [0, 1], [2, 1], [0, 1], [2, 1], [0, 1], [2, 1], [0, 1], [2, 1], [0, 1], [2, 1], [0, 1], [2, 1], [0, 1], [2, 1], [0, 1], [2, 1], [0, 1], [2, 1], [0, 1], [3, 1], [0, 1], [2, 1], [0, 1], [2, 1], [0, 1], [1, 1], [2, 28], [0, 1], [2, 10], [1, 1], [2, 16], [0, 1], [2, 1], [0, 1], [2, 1], [0, 1], [2, 1], [0, 1], [2, 1], [0, 1], [2, 1], [0, 1], [2, 1], [0, 1], [2, 1], [0, 1], [2, 1], [0, 1], [3, 1], [0, 1], [1, 1], [0, 1], [2, 1], [0, 1], [2, 1], [0, 1], [2, 1], [0, 1], [2, 1], [0, 19], [2, 1], [0, 1], [2, 1], [0, 1], [2, 1], [0, 1], [2, 1], [0, 1], [2, 4], [1, 1], [2, 13], [3, 1], [2, 4], [1, 1], [2, 5], [0, 1], [2, 22], [3, 1], [2, 4], [0, 1], [2, 1], [0, 1], [2, 1], [0, 1], [2, 1], [0, 1], [2, 1], [0, 1], [2, 1], [0, 1], [2, 1], [0, 1], [2, 1], [0, 1], [2, 1], [0, 1], [2, 1], [0, 1], [2, 1], [0, 1], [2, 1], [3, 1], [2, 1], [3, 1], [2, 1], [0, 1], [2, 1], [0, 3], [2, 1], [0, 1], [2, 1], [0, 1], [2, 1], [0, 1], [2, 1], [0, 1], [2, 1], [0, 1], [2, 1], [0, 1], [2, 1], [0, 1], [2, 1], [0, 1], [2, 1], [0, 1], [2, 1], [0, 1], [1, 1], [0, 1], [2, 1], [0, 1], [2, 23], [3, 1], [2, 5], [0, 1], [2, 4], [1, 1], [2, 22], [0, 29], [2, 1], [0, 1], [2, 1], [0, 1], [2, 1], [0, 1], [2, 1], [0, 1], [2, 1], [0, 1], [2, 1], [0, 1], [2, 1], [0, 1], [2, 1], [0, 1], [2, 1], [0, 1], [3, 1], [0, 1], [2, 1], [0, 1], [2, 1], [0, 1], [2, 1], [0, 1], [2, 15], [3, 1], [2, 13], [0, 1], [2, 2], [3, 1], [2, 9], [3, 1], [2, 1], [3, 1], [2, 12], [0, 29], [2, 1], [0, 1], [2, 1], [0, 1], [2, 1], [0, 1], [2, 1], [0, 1], [1, 1], [0, 1], [2, 1], [0, 1], [2, 1], [0, 1], [2, 1], [0, 1], [3, 2], [2, 1], [0, 1], [2, 1], [0, 1], [2, 1], [0, 1], [2, 1], [0, 1], [2, 3], [3, 2], [2, 2], [3, 1], [2, 2], [1, 1], [2, 2], [1, 1], [2, 4], [1, 1], [2, 10], [0, 1], [2, 21], [1, 1], [2, 5], [0, 1], [2, 1], [0, 1], [2, 1], [0, 1], [2, 1], [0, 1], [2, 1], [0, 1], [3, 1], [0, 1], [2, 1], [0, 1], [2, 1], [0, 1], [2, 1], [0, 1], [2, 1], [0, 1], [2, 1], [0, 1], [2, 1], [3, 1], [2, 1], [0, 1], [2, 1], [3, 1], [2, 1], [0, 1], [2, 1], [0, 1], [3, 2], [2, 1], [0, 1], [2, 1], [0, 1], [2, 1], [0, 1], [2, 1], [0, 1], [2, 1], [0, 1], [2, 1], [0, 1], [2, 1], [0, 1], [2, 1], [0, 1], [2, 1], [0, 1], [2, 1], [0, 1], [2, 1], [0, 1], [2, 7], [3, 1], [2, 18], [3, 1], [2, 2], [0, 1], [1, 1], [2, 7], [3, 1], [2, 17], [1, 1], [0, 1], [2, 1], [0, 1], [3, 1], [0, 1], [2, 1], [0, 1], [2, 1], [0, 1], [2, 1], [0, 1], [2, 1], [0, 1], [2, 1], [0, 1], [2, 1], [0, 1], [2, 1], [0, 1], [2, 1], [0, 1], [2, 1], [0, 1], [2, 1], [0, 1], [2, 1], [0, 1], [2, 1], [0, 1], [2, 1], [0, 1], [2, 1], [0, 1], [2, 1], [0, 1], [2, 1], [0, 1], [2, 1], [0, 1], [2, 1], [0, 1], [2, 1], [0, 1], [2, 1], [0, 1], [2, 1], [0, 1], [2, 1], [0, 1], [2, 1], [0, 1], [2, 1], [0, 1], [2, 1], [0, 1], [2, 5], [1, 1], [2, 10], [3, 1], [2, 12], [0, 1], [3, 1], [2, 26], [0, 1], [3, 1], [0, 1], [2, 1], [0, 1], [2, 1], [0, 1], [2, 1], [0, 1], [2, 1], [0, 1], [2, 1], [0, 1], [2, 1], [0, 1], [2, 1], [0, 1], [2, 1], [0, 1], [3, 2], [2, 1], [0, 1], [2, 1], [0, 1], [2, 1], [0, 1], [2, 1], [0, 1], [2, 1], [0, 1], [2, 1], [0, 1], [2, 1], [0, 1], [2, 1], [0, 1], [2, 1], [0, 1], [1, 1], [0, 1], [2, 1], [0, 1], [2, 1], [0, 1], [2, 1], [0, 1], [2, 1], [0, 1], [2, 1], [0, 1], [2, 1], [0, 1], [2, 1], [0, 1], [2, 20], [1, 1], [2, 8], [0, 1], [2, 13], [3, 1], [2, 5], [1, 1], [2, 4], [3, 1], [2, 2], [0, 1], [3, 1], [0, 1], [2, 1], [0, 1], [2, 1], [0, 1], [2, 1], [0, 1], [2, 1], [0, 1], [2, 1], [0, 17], [2, 1], [0, 1], [2, 1], [0, 1], [3, 1], [0, 1], [2, 1], [0, 1], [2, 1], [0, 1], [2, 1], [0, 1], [3, 1], [0, 1], [2, 1], [0, 1], [1, 1], [0, 1], [2, 1], [0, 1], [2, 1], [0, 1], [3, 1], [0, 1], [2, 1], [0, 1], [2, 14], [3, 1], [2, 14], [0, 1], [2, 15], [1, 1], [2, 11], [0, 1], [2, 1], [0, 1], [2, 1], [0, 1], [2, 1], [0, 1], [2, 1], [0, 1], [2, 1], [0, 1], [2, 1], [0, 1], [2, 1], [0, 1], [2, 1], [0, 1], [3, 1], [0, 1], [3, 1], [0, 1], [2, 1], [0, 1], [2, 1], [0, 1], [2, 1], [0, 1], [2, 1], [0, 27], [2, 17], [3, 1], [2, 2], [3, 1], [2, 8], [0, 1], [2, 5], [1, 1], [2, 4], [1, 1], [2, 1], [1, 1], [2, 14], [0, 1], [2, 1], [0, 1], [2, 1], [0, 1], [2, 1], [0, 1], [2, 1], [0, 1], [2, 1], [0, 1], [2, 1], [0, 1], [2, 1], [0, 1], [2, 1], [0, 1], [3, 1], [0, 1], [2, 1], [0, 1], [2, 1], [0, 1], [2, 1], [0, 1], [2, 1], [0, 1], [2, 1], [0, 27], [2, 5], [1, 1], [2, 2], [3, 1], [2, 3], [3, 1], [2, 21], [3, 1], [2, 22], [0, 1], [2, 1], [0, 1], [2, 1], [0, 1], [2, 34], [1, 1], [2, 9], [1, 1], [2, 38], [3, 1], [2, 1], [1, 1], [2, 30], [3, 1], [2, 24], [3, 1], [2, 6], [1, 1], [2, 1], [1, 1], [2, 7], [1, 1], [2, 13], [1, 1], [3, 1], [2, 3], [1, 1], [2, 2], [3, 1], [2, 19], [1, 1], [2, 22], [3, 1], [2, 11], [3, 1], [2, 15], [3, 1], [2, 9], [1, 1], [2, 8], [3, 1], [2, 2], [3, 1], [2, 6], [3, 1], [2, 28], [3, 1], [2, 14], [1, 1], [2, 6]]}, "portal_points": [{"from_map": 6775, "to_map": 6774, "tile_x": 54, "tile_y": 6, "edge_side": 1}, {"from_map": 6775, "to_map": 6776, "tile_x": 54, "tile_y": 34, "edge_side": 1}], "anchor_points": [{"anchor_id": "m06775_act_00", "type": "activity_anchor", "tile_x": 38, "tile_y": 10}, {"anchor_id": "m06775_act_01", "type": "activity_anchor", "tile_x": 0, "tile_y": 22}, {"anchor_id": "m06775_act_02", "type": "activity_anchor", "tile_x": 12, "tile_y": 30}, {"anchor_id": "m06775_bos_00", "type": "boss_anchor", "tile_x": 30, "tile_y": 18}, {"anchor_id": "m06775_bos_01", "type": "boss_anchor", "tile_x": 25, "tile_y": 22}, {"anchor_id": "m06775_npc_00", "type": "npc_anchor", "tile_x": 53, "tile_y": 32}, {"anchor_id": "m06775_npc_01", "type": "npc_anchor", "tile_x": 46, "tile_y": 16}, {"anchor_id": "m06775_npc_02", "type": "npc_anchor", "tile_x": 46, "tile_y": 10}, {"anchor_id": "m06775_npc_03", "type": "npc_anchor", "tile_x": 2, "tile_y": 13}, {"anchor_id": "m06775_npc_04", "type": "npc_anchor", "tile_x": 0, "tile_y": 2}, {"anchor_id": "m06775_por_00", "type": "portal_anchor", "tile_x": 0, "tile_y": 20}, {"anchor_id": "m06775_res_00", "type": "resource_anchor", "tile_x": 54, "tile_y": 10}], "spawn_zones": [], "spawn_zone_status": {"requested": 3, "generated": 0, "reason": "no_valid_area"}, "layout_hash": "eaac8210726e9f6d790735ed72aba03cb0cc57506ef9e48193c1bb83220ba94e"}