{"map_id": 6306, "uuid": "e0bddbc0-2948-5e81-9e73-01f19cb49f40", "layout_version": 1, "natural_key": "svtk_place_f5_plain_06306", "source_place_hash": "8c24e1f808951e702ca67443687a48d705073bef541483b98aaa854dcc0c394c", "source_build_rule_hash": "9a6a7f63d350dfd63656334a21d21ffe3ee2613681e42e4d9412b92e8946d06f", "topology_version": 1, "biome": "plain", "era": "f5", "zone": "trung_bo", "tier": 3, "safe_zone": false, "grid_w": 48, "grid_h": 36, "background": {"art_group": "plain_f5_t3"}, "walk_mask": {"encoding": "rle", "width": 48, "height": 36, "data": [[1, 1], [0, 2], [3, 1], [1, 1], [0, 1], [2, 1], [0, 3], [3, 1], [0, 8], [1, 1], [0, 2], [1, 1], [0, 16], [1, 2], [0, 3], [3, 1], [0, 4], [3, 1], [0, 26], [2, 1], [0, 3], [1, 1], [0, 7], [1, 1], [0, 3], [2, 1], [0, 1], [3, 2], [0, 4], [2, 1], [0, 2], [3, 1], [0, 1], [1, 1], [0, 10], [2, 1], [3, 1], [0, 3], [3, 1], [0, 2], [2, 2], [0, 8], [1, 1], [3, 2], [0, 1], [1, 1], [0, 4], [2, 1], [0, 30], [1, 1], [0, 1], [1, 1], [0, 1], [3, 1], [2, 1], [0, 7], [3, 1], [0, 6], [2, 1], [0, 2], [1, 1], [0, 2], [1, 1], [3, 1], [0, 1], [3, 2], [0, 4], [1, 1], [0, 1], [1, 3], [0, 5], [3, 1], [0, 3], [1, 1], [0, 2], [2, 1], [0, 2], [2, 1], [0, 1], [1, 1], [0, 5], [1, 1], [0, 1], [3, 1], [0, 4], [2, 1], [1, 2], [0, 2], [3, 1], [0, 1], [3, 1], [0, 1], [1, 1], [0, 5], [1, 1], [0, 19], [1, 1], [0, 5], [3, 1], [0, 1], [3, 1], [1, 1], [0, 1], [3, 1], [2, 1], [0, 3], [1, 1], [0, 2], [3, 1], [0, 3], [2, 1], [0, 1], [3, 1], [1, 1], [2, 1], [1, 1], [0, 2], [3, 1], [0, 24], [1, 1], [0, 2], [1, 1], [0, 1], [2, 1], [0, 3], [2, 1], [3, 1], [0, 2], [2, 1], [3, 2], [0, 1], [2, 1], [0, 17], [1, 2], [0, 4], [2, 1], [0, 1], [3, 2], [1, 1], [0, 5], [2, 1], [3, 1], [0, 1], [1, 1], [3, 1], [0, 4], [2, 1], [0, 1], [2, 1], [1, 1], [3, 1], [0, 2], [3, 1], [1, 1], [0, 3], [3, 1], [0, 2], [1, 1], [3, 2], [0, 2], [3, 1], [0, 1], [3, 1], [0, 1], [3, 1], [2, 2], [3, 1], [0, 4], [1, 1], [0, 3], [3, 1], [0, 3], [3, 1], [0, 3], [2, 1], [0, 2], [2, 1], [0, 6], [1, 1], [0, 1], [1, 1], [0, 6], [3, 1], [0, 3], [2, 1], [0, 5], [2, 1], [0, 10], [1, 1], [0, 1], [1, 1], [3, 1], [1, 1], [0, 1], [1, 1], [0, 4], [3, 2], [0, 2], [1, 1], [0, 3], [3, 1], [2, 1], [0, 2], [3, 1], [0, 3], [2, 1], [0, 9], [1, 1], [3, 1], [0, 3], [1, 1], [0, 5], [2, 2], [1, 1], [2, 1], [0, 5], [3, 1], [0, 6], [1, 1], [0, 1], [2, 1], [1, 1], [0, 1], [3, 1], [0, 8], [3, 2], [0, 1], [1, 1], [0, 1], [1, 1], [0, 1], [2, 1], [3, 1], [0, 6], [1, 1], [3, 1], [0, 2], [3, 2], [0, 6], [2, 1], [1, 1], [0, 3], [2, 1], [3, 1], [1, 1], [3, 1], [2, 1], [3, 1], [0, 13], [3, 2], [0, 1], [1, 1], [0, 2], [1, 1], [3, 1], [0, 1], [1, 1], [0, 2], [1, 1], [0, 2], [1, 1], [0, 1], [2, 1], [0, 4], [3, 1], [0, 4], [1, 1], [0, 1], [3, 1], [0, 1], [2, 1], [0, 1], [1, 1], [2, 1], [0, 3], [3, 1], [0, 2], [3, 1], [0, 4], [3, 1], [0, 1], [1, 1], [0, 3], [2, 1], [0, 3], [1, 1], [0, 3], [1, 1], [0, 1], [3, 1], [0, 3], [2, 1], [3, 1], [2, 1], [0, 3], [3, 1], [0, 3], [2, 1], [0, 5], [1, 1], [0, 8], [3, 1], [0, 3], [1, 1], [0, 2], [3, 1], [0, 2], [3, 1], [0, 3], [1, 1], [0, 1], [1, 1], [0, 2], [1, 1], [0, 3], [1, 3], [0, 9], [3, 1], [0, 2], [3, 1], [0, 1], [1, 1], [0, 10], [2, 1], [0, 1], [3, 1], [0, 11], [3, 1], [0, 30], [1, 1], [0, 5], [1, 1], [0, 1], [1, 1], [0, 1], [3, 1], [0, 5], [3, 1], [0, 1], [3, 1], [0, 2], [1, 1], [2, 1], [1, 1], [0, 5], [3, 1], [0, 4], [2, 1], [1, 1], [0, 1], [1, 1], [0, 2], [1, 1], [0, 5], [2, 1], [1, 1], [0, 4], [3, 1], [2, 1], [1, 1], [0, 1], [3, 1], [0, 4], [3, 1], [2, 1], [3, 1], [0, 2], [1, 1], [0, 3], [2, 1], [0, 7], [3, 1], [0, 2], [1, 1], [0, 1], [1, 1], [3, 1], [0, 6], [1, 1], [2, 1], [0, 7], [3, 1], [0, 4], [1, 1], [0, 10], [1, 1], [0, 10], [1, 1], [0, 2], [2, 2], [0, 3], [2, 1], [0, 4], [1, 1], [0, 4], [3, 1], [0, 4], [3, 1], [0, 1], [2, 1], [0, 2], [3, 1], [0, 2], [3, 1], [0, 2], [1, 1], [0, 5], [2, 1], [0, 1], [1, 1], [0, 5], [2, 1], [0, 3], [3, 1], [2, 2], [0, 27], [1, 1], [0, 1], [1, 3], [0, 3], [3, 1], [0, 1], [2, 1], [3, 1], [0, 4], [1, 1], [2, 1], [0, 7], [1, 1], [0, 4], [1, 1], [2, 1], [0, 1], [3, 1], [0, 1], [3, 1], [0, 2], [1, 1], [0, 4], [3, 1], [0, 2], [2, 1], [0, 1], [1, 2], [0, 3], [1, 1], [0, 8], [1, 1], [0, 3], [2, 1], [0, 1], [1, 1], [2, 1], [0, 2], [2, 1], [0, 21], [1, 1], [3, 1], [0, 31], [2, 1], [0, 1], [3, 1], [0, 4], [2, 1], [0, 9], [3, 1], [0, 10], [1, 1], [0, 2], [2, 1], [0, 1], [1, 1], [0, 7], [3, 1], [0, 3], [1, 2], [0, 1], [3, 1], [0, 1], [1, 2], [0, 3], [3, 1], [0, 2], [2, 1], [0, 1], [3, 1], [0, 10], [1, 1], [0, 2], [1, 1], [0, 5], [3, 2], [2, 1], [1, 1], [0, 3], [2, 1], [0, 7], [3, 1], [1, 2], [0, 2], [2, 1], [0, 2], [2, 1], [1, 1], [3, 1], [0, 5], [2, 1], [0, 2], [2, 2], [3, 1], [0, 4], [2, 1], [0, 2], [1, 1], [0, 1], [3, 1], [0, 3], [1, 1], [0, 4], [1, 1], [0, 10], [1, 1], [0, 1], [3, 1], [1, 1], [0, 4], [3, 1], [0, 5], [3, 1], [0, 1], [1, 2], [0, 7], [1, 1], [2, 1], [0, 5], [1, 1], [0, 1], [3, 1], [0, 2], [3, 1], [0, 4], [1, 1], [0, 5], [3, 1], [2, 1], [0, 7], [2, 1], [0, 5], [2, 1], [0, 4], [2, 1], [0, 2], [1, 1], [0, 4], [3, 2], [0, 1], [2, 2], [1, 1], [3, 1], [0, 4], [3, 2], [2, 1], [3, 1], [1, 1], [0, 2], [1, 1], [0, 6], [3, 1], [0, 3], [3, 1], [0, 2], [2, 1], [0, 6], [1, 1], [0, 2], [3, 1], [1, 1], [3, 1], [0, 2], [2, 1], [0, 1], [2, 1], [0, 1], [2, 1], [0, 9], [3, 2], [1, 1], [0, 3], [3, 1], [2, 1], [0, 1], [2, 1], [0, 1], [3, 1], [0, 5], [3, 1], [0, 11], [3, 1], [0, 1], [2, 1], [0, 1], [1, 1], [2, 1], [0, 3], [2, 1], [0, 7], [1, 1], [0, 3], [1, 1], [2, 1], [0, 3], [3, 1], [2, 1], [0, 2], [3, 1], [0, 1], [1, 1], [0, 8], [2, 1], [0, 16], [3, 1], [0, 5], [2, 1], [3, 2], [0, 2], [3, 1], [2, 1], [3, 1], [0, 4], [3, 1], [0, 5], [3, 2], [1, 1], [0, 4], [1, 1], [0, 1], [2, 1], [0, 5], [2, 2], [0, 4], [3, 1], [0, 14], [2, 1], [0, 2], [1, 1], [0, 2], [1, 1], [3, 1], [0, 1], [3, 1], [0, 7], [2, 1], [0, 1], [2, 1], [0, 2], [1, 1], [0, 2], [1, 1], [3, 1], [0, 1], [1, 3], [0, 6], [1, 1], [0, 1], [2, 1], [0, 1], [2, 1], [0, 2], [1, 2], [0, 5], [3, 1], [2, 1], [0, 2], [3, 1], [0, 2], [3, 1], [1, 1], [0, 2], [1, 1], [0, 4], [1, 1], [0, 1], [3, 1], [0, 1], [1, 1], [3, 1], [0, 4], [3, 1], [0, 4], [1, 1], [3, 1], [0, 4], [1, 1], [0, 3], [3, 1], [0, 2], [1, 1], [0, 3], [2, 1], [0, 1], [3, 1], [0, 1], [1, 1], [0, 4], [3, 1], [0, 2], [1, 1], [0, 1], [2, 1], [0, 2], [1, 1], [0, 1], [2, 1], [3, 1], [0, 1], [2, 1], [0, 1], [2, 1], [0, 4], [3, 1], [1, 1], [0, 2], [2, 1], [3, 2], [2, 1], [1, 1], [2, 1], [0, 3], [2, 1], [0, 2], [2, 1], [0, 2], [1, 1], [2, 1], [3, 1], [0, 1], [2, 1], [0, 1], [3, 2], [0, 1], [3, 1], [0, 10]]}, "portal_points": [{"from_map": 6306, "to_map": 6305, "tile_x": 1, "tile_y": 3, "edge_side": 0}, {"from_map": 6306, "to_map": 6307, "tile_x": 46, "tile_y": 6, "edge_side": 1}], "anchor_points": [{"anchor_id": "m06306_act_00", "type": "activity_anchor", "tile_x": 41, "tile_y": 20}, {"anchor_id": "m06306_bos_00", "type": "boss_anchor", "tile_x": 41, "tile_y": 6}, {"anchor_id": "m06306_bos_01", "type": "boss_anchor", "tile_x": 0, "tile_y": 23}, {"anchor_id": "m06306_npc_00", "type": "npc_anchor", "tile_x": 33, "tile_y": 0}, {"anchor_id": "m06306_npc_01", "type": "npc_anchor", "tile_x": 20, "tile_y": 14}, {"anchor_id": "m06306_npc_02", "type": "npc_anchor", "tile_x": 8, "tile_y": 1}, {"anchor_id": "m06306_por_00", "type": "portal_anchor", "tile_x": 0, "tile_y": 16}, {"anchor_id": "m06306_res_00", "type": "resource_anchor", "tile_x": 35, "tile_y": 5}, {"anchor_id": "m06306_res_01", "type": "resource_anchor", "tile_x": 36, "tile_y": 22}, {"anchor_id": "m06306_res_02", "type": "resource_anchor", "tile_x": 9, "tile_y": 23}], "spawn_zones": [{"zone_id": "m06306_spawn_00", "zone_type": "monster_spawn", "bounds": {"x": 6, "y": 10, "w": 8, "h": 5}, "biome": "plain", "tier": 3, "spawn_profile": "field_combat", "density_hint": "low", "walkable_ratio": 0.88, "forbidden": ["portal", "npc_anchor", "safe_zone_core"]}, {"zone_id": "m06306_spawn_01", "zone_type": "monster_spawn", "bounds": {"x": 13, "y": 15, "w": 7, "h": 3}, "biome": "plain", "tier": 3, "spawn_profile": "field_combat", "density_hint": "low", "walkable_ratio": 0.76, "forbidden": ["portal", "npc_anchor", "safe_zone_core"]}, {"zone_id": "m06306_spawn_02", "zone_type": "monster_spawn", "bounds": {"x": 32, "y": 31, "w": 6, "h": 3}, "biome": "plain", "tier": 3, "spawn_profile": "field_combat", "density_hint": "low", "walkable_ratio": 0.94, "forbidden": ["portal", "npc_anchor", "safe_zone_core"]}], "spawn_zone_status": {"requested": 3, "generated": 3, "reason": "ok"}, "layout_hash": "d81cbe14cd2e713e31d0abe7be1000740f98f31ffe3968da2ea9131ad1150ef6"}