{
  "map_id": 7476,
  "uuid": "64837c61-c69c-56c8-a21b-341ebb8f6f03",
  "natural_key": "svtk_place_f2_citadel_07476",
  "grid_w": 56,
  "grid_h": 42,
  "canvas_w": 1920,
  "canvas_h": 1080,
  "image_w": 1920,
  "image_h": 1080,
  "tile_px": 25,
  "content_x": 260,
  "content_y": 15,
  "content_w": 1400,
  "content_h": 1050,
  "content_image_w": 1400,
  "content_image_h": 1050,
  "layout_hash": "00fc59d402e58883e30732885dd0913cfe6e3bfe6d05d3adcad1ad7ab9983506",
  "safe_zone": false,
  "art_group": "citadel_f2_t4",
  "portal_count": 2,
  "anchor_count": 8,
  "spawn_zone_count": 4
}